{
    "1": 2,
    "2": 2,
    "3": 2,
    "4": 2,
    "5": 2,
    "6": 2,
    "7": 2,
    "8": 2,
    "9": 2,
    "10": 2,
    "11": 2,
    "12": 2,
    "13": 2,
    "14": 2,
    "15": 2,
    "16": 2,
    "17": 2,
    "18": 2,
    "19": 2,
    "20": 2,
    "21": 2,
    "22": 2,
    "23": 2,
    "24": 2,
    "25": 2,
    "26": 2,
    "27": 2,
    "28": 2,
    "29": 2,
    "30": 2,
    "31": 2,
    "32": 2,
    "33": 2,
    "34": 2,
    "35": 2,
    "36": 2,
    "37": 2,
    "38": 2,
    "39": 2,
    "40": 2,
    "41": 2,
    "42": 2,
    "43": 2,
    "44": 2,
    "45": 2,
    "46": 2,
    "47": 2,
    "48": 2,
    "49": 2,
    "50": 2,
    "51": 2,
    "52": 2,
    "53": 2,
    "54": 2,
    "55": 2,
    "56": 2,
    "57": 2,
    "58": 2,
    "59": 2,
    "60": 2,
    "61": 2,
    "62": 2,
    "63": 2,
    "64": 2,
    "65": 2,
    "66": 2,
    "67": 2,
    "68": 2,
    "69": 2,
    "70": 2,
    "71": 2,
    "72": 2,
    "73": 2,
    "74": 2,
    "75": 2,
    "76": 2,
    "77": 2,
    "78": 2,
    "79": 2,
    "80": 2,
    "81": 2,
    "82": 2,
    "83": 2,
    "84": 2,
    "85": 2,
    "86": 2,
    "87": 2,
    "88": 2,
    "89": 2,
    "90": 2,
    "91": 2,
    "92": 2,
    "93": 2,
    "94": 2,
    "95": 2,
    "96": 2,
    "97": 2,
    "98": 2,
    "99": 2,
    "100": 2,
    "101": 2,
    "102": 2,
    "103": 2,
    "104": 2,
    "105": 2,
    "106": 2,
    "107": 2,
    "108": 2,
    "109": 2,
    "110": 2,
    "111": 2,
    "112": 2,
    "113": 2,
    "114": 2,
    "115": 2,
    "116": 2,
    "117": 2,
    "118": 2,
    "119": 2,
    "120": 2,
    "121": 2,
    "122": 4,
    "123": 4,
    "124": 4,
    "125": 4,
    "126": 4,
    "127": 4,
    "128": 4,
    "129": 4,
    "130": 4,
    "131": 4,
    "132": 4,
    "133": 4,
    "134": 4,
    "135": 4,
    "136": 4,
    "137": 4,
    "138": 4,
    "139": 4,
    "140": 4,
    "141": 4,
    "142": 4,
    "143": 4,
    "144": 4,
    "145": 4,
    "146": 4,
    "147": 4,
    "148": 4,
    "149": 4,
    "150": 4,
    "151": 4,
    "152": 4,
    "153": 4,
    "154": 4,
    "155": 4,
    "156": 4,
    "157": 4,
    "158": 4,
    "159": 4,
    "160": 4,
    "161": 4,
    "162": 4,
    "163": 4,
    "164": 4,
    "165": 4,
    "166": 4,
    "167": 4,
    "168": 4,
    "169": 4,
    "170": 4,
    "171": 4,
    "172": 4,
    "173": 4,
    "174": 4,
    "175": 4,
    "176": 4,
    "177": 4,
    "178": 4,
    "179": 4,
    "180": 4,
    "181": 4,
    "182": 4,
    "183": 4,
    "184": 4,
    "185": 4,
    "186": 4,
    "187": 4,
    "188": 4,
    "189": 4,
    "190": 4,
    "191": 4,
    "192": 4,
    "193": 8,
    "194": 8,
    "195": 8,
    "196": 8,
    "197": 8,
    "198": 8,
    "199": 8,
    "200": 8,
    "201": 8,
    "202": 8,
    "203": 8,
    "204": 8,
    "205": 8,
    "206": 8,
    "207": 8,
    "208": 8,
    "209": 8,
    "210": 8,
    "211": 11,
    "212": 11,
    "213": 11,
    "214": 11,
    "215": 11,
    "216": 11,
    "217": 11,
    "218": 11,
    "219": 11,
    "220": 11,
    "221": 11,
    "222": 11,
    "223": 11,
    "224": 11,
    "225": 11,
    "226": 11,
    "227": 13,
    "228": 14,
    "229": 14,
    "230": 14,
    "231": 14,
    "232": 14,
    "233": 14,
    "234": 14,
    "235": 14,
    "236": 14,
    "237": 14,
    "238": 14,
    "239": 14,
    "240": 14,
    "241": 16,
    "242": 16,
    "243": 16,
    "244": 16,
    "245": 16,
    "246": 16,
    "247": 16,
    "248": 16,
    "249": 16,
    "250": 16,
    "251": 16,
    "252": 16,
    "253": 16,
    "254": 16,
    "255": 16,
    "256": 16,
    "257": 16,
    "258": 17,
    "259": 17,
    "260": 17,
    "261": 17,
    "262": 18,
    "263": 19,
    "264": 19,
    "265": 19,
    "266": 19,
    "267": 19,
    "268": 19,
    "269": 19,
    "270": 19,
    "271": 19,
    "272": 19,
    "273": 19,
    "274": 19,
    "275": 19,
    "276": 19,
    "277": 19,
    "278": 19,
    "279": 19,
    "280": 19,
    "281": 19,
    "282": 19,
    "283": 19,
    "284": 19,
    "285": 19,
    "286": 19,
    "287": 19,
    "288": 19,
    "289": 19,
    "290": 19,
    "291": 19,
    "292": 19,
    "293": 19,
    "294": 19,
    "295": 19,
    "296": 19,
    "297": 19,
    "298": 19,
    "299": 19,
    "300": 19,
    "301": 19,
    "302": 19,
    "303": 19,
    "304": 19,
    "305": 19,
    "306": 19,
    "307": 19,
    "308": 19,
    "309": 19,
    "310": 19,
    "311": 19,
    "312": 19,
    "313": 19,
    "314": 19,
    "315": 19,
    "316": 19,
    "317": 19,
    "318": 19,
    "319": 19,
    "320": 19,
    "321": 19,
    "322": 19,
    "323": 19,
    "324": 19,
    "325": 19,
    "326": 19,
    "327": 19,
    "328": 19,
    "329": 19,
    "330": 22,
    "331": 23,
    "332": 23,
    "333": 23,
    "334": 23,
    "335": 23,
    "336": 23,
    "337": 23,
    "338": 23,
    "339": 23,
    "340": 23,
    "341": 23,
    "342": 23,
    "343": 23,
    "344": 23,
    "345": 23,
    "346": 23,
    "347": 23,
    "348": 23,
    "349": 23,
    "350": 23,
    "351": 23,
    "352": 23,
    "353": 23,
    "354": 23,
    "355": 23,
    "356": 23,
    "357": 23,
    "358": 23,
    "359": 23,
    "360": 23,
    "361": 24,
    "362": 24,
    "363": 24,
    "364": 24,
    "365": 24,
    "366": 24,
    "367": 24,
    "368": 24,
    "369": 24,
    "370": 24,
    "371": 24,
    "372": 24,
    "373": 24,
    "374": 24,
    "375": 24,
    "376": 24,
    "377": 27,
    "378": 27,
    "379": 27,
    "380": 27,
    "381": 27,
    "382": 27,
    "383": 27,
    "384": 27,
    "385": 27,
    "386": 27,
    "387": 27,
    "388": 27,
    "389": 27,
    "390": 27,
    "391": 27,
    "392": 27,
    "393": 27,
    "394": 27,
    "395": 27,
    "396": 27,
    "397": 27,
    "398": 27,
    "399": 27,
    "400": 30,
    "401": 30,
    "402": 30,
    "403": 30,
    "404": 30,
    "405": 30,
    "406": 30,
    "407": 30,
    "408": 30,
    "409": 30,
    "410": 30,
    "411": 30,
    "412": 30,
    "413": 30,
    "414": 30,
    "415": 30,
    "416": 30,
    "417": 32,
    "418": 35,
    "419": 32,
    "420": 32,
    "421": 32,
    "422": 32,
    "423": 32,
    "424": 32,
    "425": 32,
    "426": 32,
    "427": 36,
    "428": 36,
    "429": 36,
    "430": 36,
    "431": 36,
    "432": 36,
    "433": 36,
    "434": 36,
    "435": 36,
    "436": 36,
    "437": 36,
    "438": 36,
    "439": 36,
    "440": 36,
    "441": 36,
    "442": 36,
    "443": 36,
    "444": 36,
    "445": 36,
    "446": 36,
    "447": 36,
    "448": 36,
    "449": 36,
    "450": 36,
    "451": 36,
    "452": 36,
    "453": 36,
    "454": 36,
    "455": 36,
    "456": 36,
    "457": 36,
    "458": 36,
    "459": 36,
    "460": 36,
    "461": 36,
    "462": 36,
    "463": 36,
    "464": 36,
    "465": 36,
    "466": 36,
    "467": 36,
    "468": 36,
    "469": 36,
    "470": 36,
    "471": 36,
    "472": 36,
    "473": 36,
    "474": 36,
    "475": 36,
    "476": 36,
    "477": 36,
    "478": 36,
    "479": 37,
    "480": 37,
    "481": 37,
    "482": 37,
    "483": 36,
    "484": 36,
    "485": 36,
    "486": 36,
    "487": 36,
    "488": 36,
    "489": 36,
    "490": 36,
    "491": 36,
    "492": 36,
    "493": 36,
    "494": 36,
    "495": 36,
    "496": 37,
    "497": 40,
    "498": 40,
    "499": 41,
    "500": 42,
    "501": 42,
    "502": 42,
    "503": 42,
    "504": 40,
    "505": 40,
    "506": 40,
    "507": 40,
    "508": 40,
    "509": 40,
    "510": 40,
    "511": 40,
    "512": 40,
    "513": 40,
    "514": 40,
    "515": 40,
    "516": 40,
    "517": 41,
    "518": 43,
    "519": 43,
    "520": 43,
    "521": 43,
    "522": 43,
    "523": 43,
    "524": 43,
    "525": 43,
    "526": 43,
    "527": 43,
    "528": 43,
    "529": 43,
    "530": 43,
    "531": 43,
    "532": 43,
    "533": 43,
    "534": 43,
    "535": 43,
    "536": 43,
    "537": 43,
    "538": 43,
    "539": 43,
    "540": 45,
    "541": 45,
    "542": 45,
    "543": 45,
    "544": 45,
    "545": 45,
    "546": 45,
    "547": 45,
    "548": 49,
    "549": 49,
    "550": 49,
    "551": 45,
    "552": 45,
    "553": 45,
    "554": 45,
    "555": 45,
    "556": 45,
    "557": 45,
    "558": 45,
    "559": 45,
    "560": 45,
    "561": 49,
    "562": 49,
    "563": 49,
    "564": 49,
    "565": 45,
    "566": 45,
    "567": 45,
    "568": 45,
    "569": 46,
    "570": 45,
    "571": 49,
    "572": 49,
    "573": 49,
    "574": 49,
    "575": 49,
    "576": 49,
    "577": 49,
    "578": 49,
    "579": 49,
    "580": 49,
    "581": 49,
    "582": 49,
    "583": 49,
    "584": 49,
    "585": 49,
    "586": 49,
    "587": 49,
    "588": 49,
    "589": 49,
    "590": 49,
    "591": 49,
    "592": 49,
    "593": 49,
    "604": 55,
    "605": 55,
    "606": 55,
    "607": 55,
    "608": 55,
    "609": 55,
    "610": 55,
    "611": 55,
    "612": 55,
    "613": 55,
    "614": 55,
    "615": 52,
    "616": 52,
    "617": 52,
    "618": 52,
    "619": 52,
    "620": 52,
    "621": 52,
    "622": 52,
    "623": 52,
    "624": 52,
    "625": 52,
    "626": 52,
    "627": 52,
    "628": 52,
    "629": 52,
    "630": 52,
    "631": 52,
    "632": 54,
    "633": 54,
    "634": 54,
    "635": 52,
    "636": 52,
    "637": 52,
    "638": 52,
    "639": 52,
    "640": 52,
    "641": 52,
    "642": 52,
    "643": 52,
    "644": 52,
    "645": 55,
    "646": 58,
    "647": 58,
    "648": 58,
    "649": 58,
    "650": 58,
    "651": 58,
    "652": 58,
    "653": 58,
    "654": 58,
    "655": 58,
    "656": 58,
    "657": 58,
    "658": 58,
    "659": 58,
    "660": 58,
    "661": 58,
    "662": 58,
    "663": 58,
    "664": 58,
    "665": 58,
    "666": 58,
    "667": 58,
    "668": 58,
    "669": 58,
    "670": 58,
    "671": 58,
    "672": 58,
    "673": 58,
    "674": 58,
    "675": 58,
    "676": 58,
    "677": 58,
    "678": 58,
    "679": 58,
    "680": 58,
    "681": 58,
    "682": 58,
    "683": 58,
    "684": 58,
    "685": 58,
    "686": 58,
    "687": 58,
    "688": 58,
    "689": 58,
    "690": 58,
    "691": 58,
    "692": 58,
    "693": 58,
    "694": 58,
    "695": 58,
    "696": 59,
    "697": 59,
    "698": 59,
    "699": 58,
    "700": 58,
    "701": 58,
    "702": 60,
    "703": 58,
    "704": 58,
    "705": 58,
    "706": 58,
    "707": 58,
    "708": 58,
    "709": 58,
    "710": 58,
    "711": 58,
    "712": 58,
    "713": 58,
    "714": 58,
    "715": 58,
    "716": 58,
    "717": 59,
    "718": 62,
    "719": 62,
    "720": 62,
    "721": 62,
    "727": 62,
    "728": 62,
    "730": 62,
    "732": 62,
    "733": 62,
    "734": 62,
    "736": 62,
    "737": 62,
    "738": 62,
    "739": 62,
    "740": 62,
    "741": 62,
    "0": 2
}